Workbook

Sheet Configuración
A1: CONFIGURACIÓN PERSONAL
A3: ¿Tiene cónyuge a cargo? | B3: NO
A4: Cantidad de hijos | B4: 0
A5: Hijos incapacitados | B5: 0
A7: Tipo de Deducción Especial: | B7: General / Profesionales / Corredores-Viajantes / Personal Antártida
A8: Seleccione: | B8: General

Sheet Parametros
A1: DEDUCCIONES PERSONALES - Enero a Junio 2025 | D1: DEDUCCIONES PERSONALES - Julio a Diciembre 2025
A3: Ganancia No Imponible (MNI) | B3: 326355.7 | D3: Ganancia No Imponible (MNI) | E3: 326355.7
A4: Deducción por Cónyuge | B4: 302130.08 | D4: Deducción por Cónyuge | E4: 302130.08
A5: Deducción por Hijo | B5: 159273.44 | D5: Deducción por Hijo | E5: 159273.44
A6: Deducción por Hijo Incapacitado | B6: 318546.87 | D6: Deducción por Hijo Incapacitado | E6: 318546.87
A8: Deducción Especial - General | B8: 1142244.9 | D8: Deducción Especial - General | E8: 1142244.9
A9: Deducción Especial - Profesionales Nuevos | B9: 1713367.4 | D9: Deducción Especial - Profesionales Nuevos | E9: 1713367.4
A10: Deducción Especial - Zona Desfavorable | B10: 1827832.9 | D10: Deducción Especial - Zona Desfavorable (NO VIGENTE 2025) | E10: 0
A13: ESCALAS PROGRESIVAS - ENERO A JUNIO 2025 (Tabla Oficial ARCA)
A14: Ganancia Neta Acumulada | B14: Hasta | C14: Pagarán | D14: Más el % | E14: Sobre excedente de
A15: 0 | B15: 126697.64 | C15: 0 | D15: 0.05 | E15: 0
A16: 126697.64 | B16: 253395.28 | C16: 6334.88 | D16: 0.09 | E16: 126697.64
A17: 253395.28 | B17: 380092.92 | C17: 17737.67 | D17: 0.12 | E17: 253395.28
A18: 380092.92 | B18: 570139.38 | C18: 32941.39 | D18: 0.15 | E18: 380092.92
A19: 570139.38 | B19: 1140278.8 | C19: 61448.36 | D19: 0.19 | E19: 570139.38
A20: 1140278.8 | B20: 1710418.1 | C20: 169774.84 | D20: 0.23 | E20: 1140278.8
A21: 1710418.1 | B21: 2565627.2 | C21: 300906.89 | D21: 0.27 | E21: 1710418.1
A22: 2565627.2 | B22: 3848440.8 | C22: 531813.34 | D22: 0.31 | E22: 2565627.2
A23: 3848440.8 | C23: 929485.56 | D23: 0.35 | E23: 3848440.8
A25: ESCALAS PROGRESIVAS - Julio a Diciembre 2025
A26: ESCALAS PROGRESIVAS - JULIO A DICIEMBRE 2025 (Tabla Oficial ARCA) | B26: Hasta | C26: Pagarás | D26: Más el % | E26: Sobre excedente de
A27: Ganancia Neta Acumulada | B27: Hasta | C27: Pagarán | D27: Más el % | E27: Sobre excedente de
A28: 0 | B28: 886883.47 | C28: 0 | D28: 0.05 | E28: 0
A29: 886883.47 | B29: 1773766.9 | C29: 44344.17 | D29: 0.09 | E29: 886883.47
A30: 1773766.9 | B30: 2660650.4 | C30: 124163.69 | D30: 0.12 | E30: 1773766.9
A31: 2660650.4 | B31: 3990975.6 | C31: 230589.7 | D31: 0.15 | E31: 2660650.4
A32: 3990975.6 | B32: 7981951.3 | C32: 430138.49 | D32: 0.19 | E32: 3990975.6
A33: 7981951.3 | B33: 11972927 | C33: 1188423.9 | D33: 0.23 | E33: 7981951.3
A34: 11972927 | B34: 17959390 | C34: 2106348.2 | D34: 0.27 | E34: 11972927
A35: 17959390 | B35: 26939086 | C35: 3722693.4 | D35: 0.31 | E35: 17959390
A36: 26939086 | C36: 6506398.9 | D36: 0.35 | E36: 26939086
A38: TOPES MoPre MENSUALES 2025 | D38: DEDUCCIONES GENERALES - TOPES | G38: Tope de la deducción: 5% de la ganancia neta del ejercicio acumulada hasta el mes que se liquida (item 6, Ganancia neta del mes que se liquida...) antes de restar de la misma, si los hubiera, los siguientes importes deducibles:
A39: Mes | B39: Tope MoPre | D39: Concepto | E39: Tope | G39: Tope5% | H39: a) donaciones permitidas (ver detalle en anexo) | I39: b) honorarios pagados por servicios de asistencia sanitaria, médica y paramédica del contribuyente y de las personas que revistan para éste el carácter de cargas de familia (ver detalle en anexo) | J39: c) quebrantos de años anteriores | K39: d) ganancia mínima no imponible (monto a deducir fijo y actualizable automáticamente por semestres según IPC acumulada del semestre) | L39: e) deducción especial (ver detalles en anexo) | M39: f) deducción especial doceava parte | N39: g) cargas de familia (ver detalle en anexo) | O39: descuentos obligatorios efectuados para aportes para obras sociales correspondientes al contribuyente y a las personas que revistan para éste el carácter de cargas de familia | P39: Importes que se destinen a cuotas o abonos a instituciones que presten cobertura médico asistencial (ej. Medicina prepaga), correspondientes al beneficiario y a las personas que revistan para el mismo el carácter de cargas de familia
A40: Enero | B40: 2910574 | D40: Medicina Prepaga | E40: 5% de GNSI | G40: Medicina prepaga
A41: Febrero | B41: 2910574 | D41: Seguro de Vida | E41: 5% de GNSI | F41: TOPE FIJO SEMESTRAL ARCA (no 5%)
A42: Marzo | B42: 2910574 | D42: Donaciones | E42: 5% de GNSI | G42: Donaciones
A43: Abril | B43: 2910574 | D43: Alquiler 40% | E43: Hasta MNI
A44: Mayo | B44: 2910574 | D44: Empleada Doméstica | E44: Hasta MNI
A45: Junio | B45: 2910574 | D45: Honorarios por servicios de asistencia médica, paramédica y sanitaria | F45: 40% por factura + Tope 5% GNSI total | G45: Honorarios por servicios de asistencia médica, paramédica y sanitaria
A46: Julio | B46: 2910574
A47: Agosto | B47: 2910574
A48: Septiembre | B48: 2910574
A49: Octubre | B49: 2910574
A50: Noviembre | B50: 2910574 | E50: Otros topes deducibles:
A51: Diciembre | B51: 3731212
F54: Tipo deducción | G54: Concepto deducible | H54: Tope deducible
F55: Deducciones generales (apartado D) | G55: - Primas de seguro para casos de muerte pagadas | H55: 2025: $573.817,13 2026: $753.472,14
G56: - Primas que cubran el riesgo de muerte y primas de ahorro (seguros mixtos), excepto para los casos de seguros retiro privados administrados por entidades sujetas al control de la Superintendencia de Seguros de la Nación, pagados | H56: 2025: $573.817,13 2026: $753.472,14
G57: - Pagos por adquisición de cuotapartes de fondos comunes de inversión que se constituyan con fines de retiro (Regulados por Comisión Nac. de Valores) | H57: 2025: $573.817,13 2026: $753.472,14
G58: - Gastos de sepelio del contribuyente o de personas a su cargo | H58: Total anual deducible $996,23
G59: - Alquileres pagados solamente por vivienda personal. Condiciones: que el alquiler sea facturado (factura o recibo) y que quien lo alquila no sea titular de ningún inmueble en ninguna proporción. Forma de computar la deducción: se permite deducir el 40% del alquiler pagado. | H59: Importe equivalente a ganancia no imponible
G60: - Intereses correspondientes a créditos hipotecarios que les hubieran sido otorgados por la compra o construcción de inmuebles destinados a la casa habitación. | H60: Total anual deducible $20.000
G61: - Importes abonados al personal que trabaja en casas particulares (haberes + aportes jubilatorio, obra social y ART). Condición: personal registrado y emitido el recibo correspondiente. | H61: Importe equivalente a ganancia no imponible
G62: - Aportes correspondientes a los planes de seguro de retiro privados administrados por entidades sujetas al control de la Superintendencia de Seguros de la Nación | H62: 2025: $573.817,13 2026: $753.472,14
G63: - Sumas en concepto de servicios con fines educativos y de las herramientas destinadas a esos efectos pagadas por cargas de familia, de hasta 24 años inclusive (incapacitados para el trabajo sín límites de edad) en tanto cursen estudios regulares o profesionales de un arte u oficio, que les impida proveerse de medios necesarios para sostenerse independientemente y que no tengan en el año ingresos netos superiores al importe de la "ganancia no imponible del punto 9). | H63: Importe equivalente a 40% de ganancia no imponible
G64: - Importe adicional alquileres pagados solamente por vivienda personal. Este adicional es deducible tanto por el locatario (quien alquila) como por el locador (el dueño del inmueble). Condiciones generales: que el alquiler sea facturado (factura o recibo) y que el contrato de alquiler esté registrado en ARCA en el servicio "Registro de locación de inmuebles - RELI". Condición adicional solo locatario: que quien lo alquila no sea titular de ningún inmueble en ninguna proporción. Forma de computar la deducción: se permite deducir el 10% del alquiler pagado. | H64: Importe equivalente a ganancia no imponible
F65: Deducciones personales (apartado E) | G65: Ganancias no imponibles | H65: 2025: $4.507.505,52
G66: Cargas de familia - cónyuge | H66: 2025: $4.245.166,13
G67: Cargas de familia - Hijos | H67: 2025: $2.140.852,77
G68: Cargas de familia - Hijos incapacitados para el trabajo | H68: 2025: $4.281.705,53
G69: Deducción especial - Para trabajadores bajo relación dependencia / desempeño de cargos públicos y jubilados no incluidos en punto siguiente | H69: 2025: $21.636.026,50
G70: Para jubilados que no tengan otros ingresos adicionales a la jubilación/pensión etc y no tributen bienes personales (evento condicional) | H70: 12/2025: $349.299,32 Tope deducible : $2.794.394,56

Sheet Liquidación Anual 2025
A1: CONCEPTO | B1: Ene | C1: Feb | D1: Mar | E1: Abr | F1: May | G1: Jun | H1: Jul | I1: Ago | J1: Sep | K1: Oct | L1: Nov | M1: Dic
A2: LIQUIDACIÓN ANUAL 2025 - IMPUESTO A LAS GANANCIAS (4ta CATEGORÍA)
A3: 1. INGRESOS DEL MES
A4: Sueldo Básico | B4: 5927497 | C4: 0 | D4: 0 | E4: 0 | F4: 0 | G4: 0 | H4: 0 | I4: 0 | J4: 0 | K4: 0 | L4: 0 | M4: 0
A5: Adicionales Habituales | B5: 0 | C5: 0 | D5: 0 | E5: 0 | F5: 0 | G5: 0 | H5: 0 | I5: 0 | J5: 0 | K5: 0 | L5: 0 | M5: 0
A6: Antigüedad | B6: 0 | C6: 0 | D6: 0 | E6: 0 | F6: 0 | G6: 0 | H6: 0 | I6: 0 | J6: 0 | K6: 0 | L6: 0 | M6: 0
A7: Comisiones | B7: 0 | C7: 0 | D7: 0 | E7: 0 | F7: 0 | G7: 0 | H7: 0 | I7: 0 | J7: 0 | K7: 0 | L7: 0 | M7: 0
A8: Plus Vacacional | B8: 0 | C8: 0 | D8: 0 | E8: 0 | F8: 0 | G8: 0 | H8: 0 | I8: 0 | J8: 0 | K8: 0 | L8: 0 | M8: 0
A9: Otros Conceptos Remunerativos | B9: 0 | C9: 0 | D9: 0 | E9: 0 | F9: 0 | G9: 0 | H9: 0 | I9: 0 | J9: 0 | K9: 0 | L9: 0 | M9: 0
A10: Conceptos No Remunerativos Habituales | B10: 0 | C10: 0 | D10: 0 | E10: 0 | F10: 0 | G10: 0 | H10: 0 | I10: 0 | J10: 0 | K10: 0 | L10: 0 | M10: 0
A11: Conceptos No Remunerativos No Habituales | B11: 0 | C11: 0 | D11: 0 | E11: 0 | F11: 0 | G11: 0 | H11: 0 | I11: 0 | J11: 0 | K11: 0 | L11: 0 | M11: 0
A12: SAC / Aguinaldo | B12: 0 | C12: 0 | D12: 0 | E12: 0 | F12: 0 | G12: 0 | H12: 0 | I12: 0 | J12: 0 | K12: 0 | L12: 0 | M12: 0
A13: Total Ingresos del Mes | B13: =B4+B5+B6+B7+B8+B9+B10+B11+B12 | C13: =C4+C5+C6+C7+C8+C9+C10+C11+C12 | D13: =D4+D5+D6+D7+D8+D9+D10+D11+D12 | E13: =E4+E5+E6+E7+E8+E9+E10+E11+E12 | F13: =F4+F5+F6+F7+F8+F9+F10+F11+F12 | G13: =G4+G5+G6+G7+G8+G9+G10+G11+G12 | H13: =H4+H5+H6+H7+H8+H9+H10+H11+H12 | I13: =I4+I5+I6+I7+I8+I9+I10+I11+I12 | ... M13: =M4+M5+M6+M7+M8+M9+M10+M11+M12
A14: 2. PLURIEMPLEO (Otros empleos)
A15: Retribuciones Habituales Pluriempleo | B15: 0 | C15: 0 | D15: 0 | E15: 0 | F15: 0 | G15: 0 | H15: 0 | I15: 0 | J15: 0 | K15: 0 | L15: 0 | M15: 0
A16: Retribuciones No Habituales Pluriempleo | B16: 0 | C16: 0 | D16: 0 | E16: 0 | F16: 0 | G16: 0 | H16: 0 | I16: 0 | J16: 0 | K16: 0 | L16: 0 | M16: 0
A17: SAC Pluriempleo | B17: 0 | C17: 0 | D17: 0 | E17: 0 | F17: 0 | G17: 0 | H17: 0 | I17: 0 | J17: 0 | K17: 0 | L17: 0 | M17: 0
A18: Total Pluriempleo | B18: =B15+B16+B17 | C18: =C15+C16+C17 | D18: =D15+D16+D17 | E18: =E15+E16+E17 | F18: =F15+F16+F17 | G18: =G15+G16+G17 | H18: =H15+H16+H17 | I18: =I15+I16+I17 | ... M18: =M15+M16+M17
A19: 3. DESCUENTOS OBLIGATORIOS
A20: Base para Descuentos (con tope MoPre) | B20: =MIN(B4+B5+B6+B7+B8+B9+B12+B15+B17,2910574) | C20: =MIN(C4+C5+C6+C7+C8+C9+C12+C15+C17,2910574) | D20: =MIN(D4+D5+D6+D7+D8+D9+D12+D15+D17,2910574) | E20: =MIN(E4+E5+E6+E7+E8+E9+E12+E15+E17,2910574) | F20: =MIN(F4+F5+F6+F7+F8+F9+F12+F15+F17,2910574) | G20: =MIN(G4+G5+G6+G7+G8+G9+G12+G15+G17,2910574) | H20: =MIN(H4+H5+H6+H7+H8+H9+H12+H15+H17,2910574) | I20: =MIN(I4+I5+I6+I7+I8+I9+I12+I15+I17,2910574) | ... L20: =MIN(L4+L5+L6+L7+L8+L9+L12+L15+L17,2910574) | M20: =MIN(M4+M5+M6+M7+M8+M9+M12+M15+M17,3731212)
A21: Jubilación 11% | B21: =B20*0.11 | C21: =C20*0.11 | D21: =D20*0.11 | E21: =E20*0.11 | F21: =F20*0.11 | G21: =G20*0.11 | H21: =H20*0.11 | I21: =I20*0.11 | ... M21: =M20*0.11
A22: Obra Social 3% | B22: =B20*0.03 | C22: =C20*0.03 | D22: =D20*0.03 | E22: =E20*0.03 | F22: =F20*0.03 | G22: =G20*0.03 | H22: =H20*0.03 | I22: =I20*0.03 | ... M22: =M20*0.03
A23: INSSJP - Ley 19.032 3% | B23: =B20*0.03 | C23: =C20*0.03 | D23: =D20*0.03 | E23: =E20*0.03 | F23: =F20*0.03 | G23: =G20*0.03 | H23: =H20*0.03 | I23: =I20*0.03 | ... M23: =M20*0.03
A24: Aportes Sindicales | B24: 0 | C24: 0 | D24: 0 | E24: 0 | F24: 0 | G24: 0 | H24: 0 | I24: 0 | J24: 0 | K24: 0 | L24: 0 | M24: 0
A25: Otros Descuentos Obligatorios por Ley | B25: 0 | C25: 0 | D25: 0 | E25: 0 | F25: 0 | G25: 0 | H25: 0 | I25: 0 | J25: 0 | K25: 0 | L25: 0 | M25: 0
A26: Total Descuentos | B26: =SUM(B20:B25) | C26: =SUM(C20:C25) | D26: =SUM(D20:D25) | E26: =SUM(E20:E25) | F26: =SUM(F20:F25) | G26: =SUM(G20:G25) | H26: =SUM(H20:H25) | I26: =SUM(I20:I25) | ... M26: =SUM(M20:M25)
A27: 4. GANANCIA BRUTA
A28: Ganancia Bruta del Mes | B28: =B13+B18-B25 | C28: =C13+C18-C25 | D28: =D13+D18-D25 | E28: =E13+E18-E25 | F28: =F13+F18-F25 | G28: =G13+G18-G25 | H28: =H13+H18-H25 | I28: =I13+I18-I25 | ... M28: =M13+M18-M25
A29: SAC Proporcional (Acum/12) | B29: =B31/12 | C29: =C31/12 | D29: =D31/12 | E29: =E31/12 | F29: =F31/12 | G29: =G31/12 | H29: =H31/12 | I29: =I31/12 | ... M29: =M31/12
A30: Ajuste SAC Semestral (Jun/Dic) | B30: 0 | C30: 0 | D30: 0 | E30: 0 | F30: 0 | G30: =G12-G28*6 | H30: 0 | I30: 0 | J30: 0 | K30: 0 | L30: 0 | M30: =M12-M28*12
A31: Ganancia Bruta con SAC Proporcional | B31: =B27+B28+B29 | C31: =C27+C28+C29 | D31: =D27+D28+D29 | E31: =E27+E28+E29 | F31: =F27+F28+F29 | G31: =G27+G28+G29 | H31: =H27+H28+H29 | I31: =I27+I28+I29 | ... M31: =M27+M28+M29
A32: Ganancia Bruta Acumulada | B32: =B27 | C32: =B31+C27 | D32: =C31+D27 | E32: =D31+E27 | F32: =E31+F27 | G32: =F31+G27 | H32: =G31+H27 | I32: =H31+I27 | J32: =I31+J27 | ... M32: =L31+M27
A33: Promedio Remuneración Bruta (para DEA) | B33: =B27 | C33: =AVERAGE(B27:C27) | D33: =AVERAGE(B27:D27) | E33: =AVERAGE(B27:E27) | F33: =AVERAGE(B27:F27) | G33: =AVERAGE(B27:G27) | H33: =AVERAGE(B27:H27) | I33: =AVERAGE(B27:I27) | J33: =AVERAGE(B27:J27) | K33: =AVERAGE(B27:K27) | L33: =AVERAGE(B27:L27) | M33: =AVERAGE(B27:M27)
A34: 5. DEDUCCIONES GENERALES
A35: Alquiler pagado (monto total) | B35: 0 | C35: 0 | D35: 0 | E35: 0 | F35: 0 | G35: 0 | H35: 0 | I35: 0 | J35: 0 | K35: 0 | L35: 0 | M35: 0
A36: Alquiler 40% (hasta MNI) | B36: =MIN(B34*0.4,Parametros!$B$3) | C36: =MIN(C34*0.4,Parametros!$B$3) | D36: =MIN(D34*0.4,Parametros!$B$3) | E36: =MIN(E34*0.4,Parametros!$B$3) | F36: =MIN(F34*0.4,Parametros!$B$3) | G36: =MIN(G34*0.4,Parametros!$B$3) | H36: =MIN(H34*0.4,Parametros!$E$3) | I36: =MIN(I34*0.4,Parametros!$E$3) | J36: =MIN(J34*0.4,Parametros!$E$3) | K36: =MIN(K34*0.4,Parametros!$E$3) | L36: =MIN(L34*0.4,Parametros!$E$3) | M36: =MIN(M34*0.4,Parametros!$E$3)
A37: Alquiler 10% Ley 27.737 | B37: =B34*0.1 | C37: =C34*0.1 | D37: =D34*0.1 | E37: =E34*0.1 | F37: =F34*0.1 | G37: =G34*0.1 | H37: =H34*0.1 | I37: =I34*0.1 | ... M37: =M34*0.1
A38: Medicina Prepaga (monto pagado) | B38: 0 | C38: 0 | D38: 0 | E38: 0 | F38: 0 | G38: 0 | H38: 0 | I38: 0 | J38: 0 | K38: 0 | L38: 0 | M38: 0
A39: Medicina Prepaga (deducible 5% GNSI) | B39: =MIN(B37,B31*0.05) | C39: =MIN(C37,C31*0.05) | D39: =MIN(D37,D31*0.05) | E39: =MIN(E37,E31*0.05) | F39: =MIN(F37,F31*0.05) | G39: =MIN(G37,G31*0.05) | H39: =MIN(H37,H31*0.05) | I39: =MIN(I37,I31*0.05) | ... M39: =MIN(M37,M31*0.05)
A40: Gastos de Educación (pagados) | B40: 0 | C40: 0 | D40: 0 | E40: 0 | F40: 0 | G40: 0 | H40: 0 | I40: 0 | J40: 0 | K40: 0 | L40: 0 | M40: 0
A41: Gastos de Educación (deducibles) | B41: =B39 | C41: =C39 | D41: =D39 | E41: =E39 | F41: =F39 | G41: =G39 | H41: =H39 | I41: =I39 | ... M41: =M39
A42: Primas Seguro de Vida (pagadas) | B42: 0 | C42: 0 | D42: 0 | E42: 0 | F42: 0 | G42: 0 | H42: 0 | I42: 0 | J42: 0 | K42: 0 | L42: 0 | M42: 0
A43: Primas Seguro Vida (deducibles 5% GNSI) | B43: =MIN(B41,B31*0.05) | C43: =MIN(C41,C31*0.05) | D43: =MIN(D41,D31*0.05) | E43: =MIN(E41,E31*0.05) | F43: =MIN(F41,F31*0.05) | G43: =MIN(G41,G31*0.05) | H43: =MIN(H41,H31*0.05) | I43: =MIN(I41,I31*0.05) | ... M43: =MIN(M41,M31*0.05)
A44: Servicio Doméstico | B44: 0 | C44: 0 | D44: 0 | E44: 0 | F44: 0 | G44: 0 | H44: 0 | I44: 0 | J44: 0 | K44: 0 | L44: 0 | M44: 0
A45: Intereses Hipotecarios | B45: 0 | C45: 0 | D45: 0 | E45: 0 | F45: 0 | G45: 0 | H45: 0 | I45: 0 | J45: 0 | K45: 0 | L45: 0 | M45: 0
A46: Donaciones (monto donado) | B46: 0 | C46: 0 | D46: 0 | E46: 0 | F46: 0 | G46: 0 | H46: 0 | I46: 0 | J46: 0 | K46: 0 | L46: 0 | M46: 0
A47: Donaciones (deducibles 5% GNSI) | B47: =MIN(B45,B31*0.05) | C47: =MIN(C45,C31*0.05) | D47: =MIN(D45,D31*0.05) | E47: =MIN(E45,E31*0.05) | F47: =MIN(F45,F31*0.05) | G47: =MIN(G45,G31*0.05) | H47: =MIN(H45,H31*0.05) | I47: =MIN(I45,I31*0.05) | ... M47: =MIN(M45,M31*0.05)
A48: Otras Deducciones Generales | B48: 0 | C48: 0 | D48: 0 | E48: 0 | F48: 0 | G48: 0 | H48: 0 | I48: 0 | J48: 0 | K48: 0 | L48: 0 | M48: 0
A49: Deducciones sobre SAC Proporcional | B49: =B28*0.17 | C49: =C28*0.17 | D49: =D28*0.17 | E49: =E28*0.17 | F49: =F28*0.17 | G49: =G28*0.17 | H49: =H28*0.17 | I49: =I28*0.17 | ... M49: =M28*0.17
A50: Primas Seguro de Seguros Mixtos | B50: 0 | C50: 0 | D50: 0 | E50: 0 | F50: 0 | G50: 0 | H50: 0 | I50: 0 | J50: 0 | K50: 0 | L50: 0 | M50: 0
A51: Pagos FCI con Fines de Retiro | B51: 0 | C51: 0 | D51: 0 | E51: 0 | F51: 0 | G51: 0 | H51: 0 | I51: 0 | J51: 0 | K51: 0 | L51: 0 | M51: 0
A52: Gastos de Sepelio | B52: 0 | C52: 0 | D52: 0 | E52: 0 | F52: 0 | G52: 0 | H52: 0 | I52: 0 | J52: 0 | K52: 0 | L52: 0 | M52: 0
A53: Amortización Automotor (Corredores/Viajantes) | B53: 0 | C53: 0 | D53: 0 | E53: 0 | F53: 0 | G53: 0 | H53: 0 | I53: 0 | J53: 0 | K53: 0 | L53: 0 | M53: 0
A54: Gastos Médicos | B54: 0 | C54: 0 | D54: 0 | E54: 0 | F54: 0 | G54: 0 | H54: 0 | I54: 0 | J54: 0 | K54: 0 | L54: 0 | M54: 0
A55: Aportes SGR | B55: 0 | C55: 0 | D55: 0 | E55: 0 | F55: 0 | G55: 0 | H55: 0 | I55: 0 | J55: 0 | K55: 0 | L55: 0 | M55: 0
A56: Aportes Planes Seguro Retiro Privados | B56: 0 | C56: 0 | D56: 0 | E56: 0 | F56: 0 | G56: 0 | H56: 0 | I56: 0 | J56: 0 | K56: 0 | L56: 0 | M56: 0
A57: Gastos Equipamiento Obligatorio Trabajo | B57: 0 | C57: 0 | D57: 0 | E57: 0 | F57: 0 | G57: 0 | H57: 0 | I57: 0 | J57: 0 | K57: 0 | L57: 0 | M57: 0
A58: Adicionales Personal Antártida | B58: 0 | C58: 0 | D58: 0 | E58: 0 | F58: 0 | G58: 0 | H58: 0 | I58: 0 | J58: 0 | K58: 0 | L58: 0 | M58: 0
A59: Total Deducciones Generales | B59: =SUM(B35:B58) | C59: =SUM(C35:C58) | D59: =SUM(D35:D58) | E59: =SUM(E35:E58) | F59: =SUM(F35:F58) | G59: =SUM(G35:G58) | H59: =SUM(H35:H58) | I59: =SUM(I35:I58) | ... M59: =SUM(M35:M58)
A60: Deducciones Generales Acumuladas | B60: =B49 | C60: =B50+C49 | D60: =C50+D49 | E60: =D50+E49 | F60: =E50+F49 | G60: =F50+G49 | H60: =G50+H49 | I60: =H50+I49 | J60: =I50+J49 | ... M60: =L50+M49
A61: 6. DEDUCCIONES PERSONALES
A62: Ganancia No Imponible (MNI) | B62: =Parametros!$B$3 | C62: =Parametros!$B$3 | D62: =Parametros!$B$3 | E62: =Parametros!$B$3 | F62: =Parametros!$B$3 | G62: =Parametros!$B$3 | H62: =Parametros!$E$3 | I62: =Parametros!$E$3 | J62: =Parametros!$E$3 | K62: =Parametros!$E$3 | L62: =Parametros!$E$3 | M62: =Parametros!$E$3
A63: Deducción por Cónyuge | B63: =IF(Configuración!$B$3="SI",Parametros!$B$4,0) | C63: =IF(Configuración!$B$3="SI",Parametros!$B$4,0) | D63: =IF(Configuración!$B$3="SI",Parametros!$B$4,0) | E63: =IF(Configuración!$B$3="SI",Parametros!$B$4,0) | F63: =IF(Configuración!$B$3="SI",Parametros!$B$4,0) | G63: =IF(Configuración!$B$3="SI",Parametros!$B$4,0) | H63: =IF(Configuración!$B$3="SI",Parametros!$E$4,0) | I63: =IF(Configuración!$B$3="SI",Parametros!$E$4,0) | J63: =IF(Configuración!$B$3="SI",Parametros!$E$4,0) | K63: =IF(Configuración!$B$3="SI",Parametros!$E$4,0) | L63: =IF(Configuración!$B$3="SI",Parametros!$E$4,0) | M63: =IF(Configuración!$B$3="SI",Parametros!$E$4,0)
A64: Deducción por Hijos | B64: =Configuración!$B$4*Parametros!$B$5 | C64: =Configuración!$B$4*Parametros!$B$5 | D64: =Configuración!$B$4*Parametros!$B$5 | E64: =Configuración!$B$4*Parametros!$B$5 | F64: =Configuración!$B$4*Parametros!$B$5 | G64: =Configuración!$B$4*Parametros!$B$5 | H64: =Configuración!$B$4*Parametros!$E$5 | I64: =Configuración!$B$4*Parametros!$E$5 | J64: =Configuración!$B$4*Parametros!$E$5 | K64: =Configuración!$B$4*Parametros!$E$5 | L64: =Configuración!$B$4*Parametros!$E$5 | M64: =Configuración!$B$4*Parametros!$E$5
A65: Deducción por Hijos Incapacitados | B65: =Configuración!$B$5*Parametros!$B$6 | C65: =Configuración!$B$5*Parametros!$B$6 | D65: =Configuración!$B$5*Parametros!$B$6 | E65: =Configuración!$B$5*Parametros!$B$6 | F65: =Configuración!$B$5*Parametros!$B$6 | G65: =Configuración!$B$5*Parametros!$B$6 | H65: =Configuración!$B$5*Parametros!$E$6 | I65: =Configuración!$B$5*Parametros!$E$6 | J65: =Configuración!$B$5*Parametros!$E$6 | K65: =Configuración!$B$5*Parametros!$E$6 | L65: =Configuración!$B$5*Parametros!$E$6 | M65: =Configuración!$B$5*Parametros!$E$6
A66: Deducción Especial (según tipo) | B66: =IF(Configuración!$B$8="Profesionales",Parametros!$B$9,IF(Configuración!$B$8="Zona Desfavorable",Parametros!$B$10,Parametros!$B$8)) | C66: =IF(Configuración!$B$8="Profesionales",Parametros!$B$9,IF(Configuración!$B$8="Zona Desfavorable",Parametros!$B$10,Parametros!$B$8)) | D66: =IF(Configuración!$B$8="Profesionales",Parametros!$B$9,IF(Configuración!$B$8="Zona Desfavorable",Parametros!$B$10,Parametros!$B$8)) | E66: =IF(Configuración!$B$8="Profesionales",Parametros!$B$9,IF(Configuración!$B$8="Zona Desfavorable",Parametros!$B$10,Parametros!$B$8)) | F66: =IF(Configuración!$B$8="Profesionales",Parametros!$B$9,IF(Configuración!$B$8="Zona Desfavorable",Parametros!$B$10,Parametros!$B$8)) | G66: =IF(Configuración!$B$8="Profesionales",Parametros!$B$9,IF(Configuración!$B$8="Zona Desfavorable",Parametros!$B$10,Parametros!$B$8)) | H66: =IF(Configuración!$B$8="Profesionales",Parametros!$E$9,IF(Configuración!$B$8="Zona Desfavorable",Parametros!$E$10,Parametros!$E$8)) | I66: =IF(Configuración!$B$8="Profesionales",Parametros!$E$9,IF(Configuración!$B$8="Zona Desfavorable",Parametros!$E$10,Parametros!$E$8)) | J66: =IF(Configuración!$B$8="Profesionales",Parametros!$E$9,IF(Configuración!$B$8="Zona Desfavorable",Parametros!$E$10,Parametros!$E$8)) | K66: =IF(Configuración!$B$8="Profesionales",Parametros!$E$9,IF(Configuración!$B$8="Zona Desfavorable",Parametros!$E$10,Parametros!$E$8)) | L66: =IF(Configuración!$B$8="Profesionales",Parametros!$E$9,IF(Configuración!$B$8="Zona Desfavorable",Parametros!$E$10,Parametros!$E$8)) | M66: =IF(Configuración!$B$8="Profesionales",Parametros!$E$9,IF(Configuración!$B$8="Zona Desfavorable",Parametros!$E$10,Parametros!$E$8))
A67: Deducción Especial Incrementada 22% (Ley 27.743) | B67: =B56*0.22 | C67: =C56*0.22 | D67: =D56*0.22 | E67: =E56*0.22 | F67: =F56*0.22 | G67: =G56*0.22 | H67: =H56*0.22 | I67: =I56*0.22 | ... M67: =M56*0.22
A68: Total Deducciones Personales | B68: =B52+B53+B54+B55+B56+B57 | C68: =C52+C53+C54+C55+C56+C57 | D68: =D52+D53+D54+D55+D56+D57 | E68: =E52+E53+E54+E55+E56+E57 | F68: =F52+F53+F54+F55+F56+F57 | G68: =G52+G53+G54+G55+G56+G57 | H68: =H52+H53+H54+H55+H56+H57 | I68: =I52+I53+I54+I55+I56+I57 | ... M68: =M52+M53+M54+M55+M56+M57
A69: 7. GANANCIA NETA IMPONIBLE
A70: Deducciones Totales Acumuladas | B70: =B50+B58 | C70: =C50+C58 | D70: =D50+D58 | E70: =E50+E58 | F70: =F50+F58 | G70: =G50+G58 | H70: =H50+H58 | I70: =I50+I58 | ... M70: =M50+M58
A71: Ganancia Neta Imponible | B71: =MAX(B31-B60,0) | C71: =MAX(C31-C60,0) | D71: =MAX(D31-D60,0) | E71: =MAX(E31-E60,0) | F71: =MAX(F31-F60,0) | G71: =MAX(G31-G60,0) | H71: =MAX(H31-H60,0) | I71: =MAX(I31-I60,0) | ... M71: =MAX(M31-M60,0)
A72: 8. IMPUESTO Y RETENCIÓN
A73: Impuesto Determinado (escalas progresivas) | B73: =IF(B59<=Parametros!$B$15,B59*Parametros!$D$15,IF(B59<=Parametros!$B$16,Parametros!$C$16+(B59-Parametros!$E$16)*Parametros!$D$16,IF(B59<=Parametros!$B$17,Parametros!$C$17+(B59-Parametros!$E$17)*Parametros!$D$17,IF(B59<=Parametros!$B$18,Parametros!$C$18+(B59-Parametros!$E$18)*Parametros!$D$18,IF(B59<=Parametros!$B$19,Parametros!$C$19+(B59-Parametros!$E$19)*Parametros!$D$19,IF(B59<=Parametros!$B$20,Parametros!$C$20+(B59-Parametros!$E$20)*Parametros!$D$20,IF(B59<=Parametros!$B$21,Parametros!$C$21+(B59-Parametros!$E$21)*Parametros!$D$21,IF(B59<=Parametros!$B$22,Parametros!$C$22+(B59-Parametros!$E$22)*Parametros!$D$22,IF(B59<=Parametros!$B$23,Parametros!$C$23+(B59-Parametros!$E$23)*Parametros!$D$23,Parametros!$C$24+(B59-Parametros!$E$24)*Parametros!$D$24))))))))) | C73: =IF(C59<=Parametros!$B$15,C59*Parametros!$D$15,IF(C59<=Parametros!$B$16,Parametros!$C$16+(C59-Parametros!$E$16)*Parametros!$D$16,IF(C59<=Parametros!$B$17,Parametros!$C$17+(C59-Parametros!$E$17)*Parametros!$D$17,IF(C59<=Parametros!$B$18,Parametros!$C$18+(C59-Parametros!$E$18)*Parametros!$D$18,IF(C59<=Parametros!$B$19,Parametros!$C$19+(C59-Parametros!$E$19)*Parametros!$D$19,IF(C59<=Parametros!$B$20,Parametros!$C$20+(C59-Parametros!$E$20)*Parametros!$D$20,IF(C59<=Parametros!$B$21,Parametros!$C$21+(C59-Parametros!$E$21)*Parametros!$D$21,IF(C59<=Parametros!$B$22,Parametros!$C$22+(C59-Parametros!$E$22)*Parametros!$D$22,IF(C59<=Parametros!$B$23,Parametros!$C$23+(C59-Parametros!$E$23)*Parametros!$D$23,Parametros!$C$24+(C59-Parametros!$E$24)*Parametros!$D$24))))))))) | D73: =IF(D59<=Parametros!$B$15,D59*Parametros!$D$15,IF(D59<=Parametros!$B$16,Parametros!$C$16+(D59-Parametros!$E$16)*Parametros!$D$16,IF(D59<=Parametros!$B$17,Parametros!$C$17+(D59-Parametros!$E$17)*Parametros!$D$17,IF(D59<=Parametros!$B$18,Parametros!$C$18+(D59-Parametros!$E$18)*Parametros!$D$18,IF(D59<=Parametros!$B$19,Parametros!$C$19+(D59-Parametros!$E$19)*Parametros!$D$19,IF(D59<=Parametros!$B$20,Parametros!$C$20+(D59-Parametros!$E$20)*Parametros!$D$20,IF(D59<=Parametros!$B$21,Parametros!$C$21+(D59-Parametros!$E$21)*Parametros!$D$21,IF(D59<=Parametros!$B$22,Parametros!$C$22+(D59-Parametros!$E$22)*Parametros!$D$22,IF(D59<=Parametros!$B$23,Parametros!$C$23+(D59-Parametros!$E$23)*Parametros!$D$23,Parametros!$C$24+(D59-Parametros!$E$24)*Parametros!$D$24))))))))) | E73: =IF(E59<=Parametros!$B$15,E59*Parametros!$D$15,IF(E59<=Parametros!$B$16,Parametros!$C$16+(E59-Parametros!$E$16)*Parametros!$D$16,IF(E59<=Parametros!$B$17,Parametros!$C$17+(E59-Parametros!$E$17)*Parametros!$D$17,IF(E59<=Parametros!$B$18,Parametros!$C$18+(E59-Parametros!$E$18)*Parametros!$D$18,IF(E59<=Parametros!$B$19,Parametros!$C$19+(E59-Parametros!$E$19)*Parametros!$D$19,IF(E59<=Parametros!$B$20,Parametros!$C$20+(E59-Parametros!$E$20)*Parametros!$D$20,IF(E59<=Parametros!$B$21,Parametros!$C$21+(E59-Parametros!$E$21)*Parametros!$D$21,IF(E59<=Parametros!$B$22,Parametros!$C$22+(E59-Parametros!$E$22)*Parametros!$D$22,IF(E59<=Parametros!$B$23,Parametros!$C$23+(E59-Parametros!$E$23)*Parametros!$D$23,Parametros!$C$24+(E59-Parametros!$E$24)*Parametros!$D$24))))))))) | F73: =IF(F59<=Parametros!$B$15,F59*Parametros!$D$15,IF(F59<=Parametros!$B$16,Parametros!$C$16+(F59-Parametros!$E$16)*Parametros!$D$16,IF(F59<=Parametros!$B$17,Parametros!$C$17+(F59-Parametros!$E$17)*Parametros!$D$17,IF(F59<=Parametros!$B$18,Parametros!$C$18+(F59-Parametros!$E$18)*Parametros!$D$18,IF(F59<=Parametros!$B$19,Parametros!$C$19+(F59-Parametros!$E$19)*Parametros!$D$19,IF(F59<=Parametros!$B$20,Parametros!$C$20+(F59-Parametros!$E$20)*Parametros!$D$20,IF(F59<=Parametros!$B$21,Parametros!$C$21+(F59-Parametros!$E$21)*Parametros!$D$21,IF(F59<=Parametros!$B$22,Parametros!$C$22+(F59-Parametros!$E$22)*Parametros!$D$22,IF(F59<=Parametros!$B$23,Parametros!$C$23+(F59-Parametros!$E$23)*Parametros!$D$23,Parametros!$C$24+(F59-Parametros!$E$24)*Parametros!$D$24))))))))) | G73: =IF(G59<=Parametros!$B$15,G59*Parametros!$D$15,IF(G59<=Parametros!$B$16,Parametros!$C$16+(G59-Parametros!$E$16)*Parametros!$D$16,IF(G59<=Parametros!$B$17,Parametros!$C$17+(G59-Parametros!$E$17)*Parametros!$D$17,IF(G59<=Parametros!$B$18,Parametros!$C$18+(G59-Parametros!$E$18)*Parametros!$D$18,IF(G59<=Parametros!$B$19,Parametros!$C$19+(G59-Parametros!$E$19)*Parametros!$D$19,IF(G59<=Parametros!$B$20,Parametros!$C$20+(G59-Parametros!$E$20)*Parametros!$D$20,IF(G59<=Parametros!$B$21,Parametros!$C$21+(G59-Parametros!$E$21)*Parametros!$D$21,IF(G59<=Parametros!$B$22,Parametros!$C$22+(G59-Parametros!$E$22)*Parametros!$D$22,IF(G59<=Parametros!$B$23,Parametros!$C$23+(G59-Parametros!$E$23)*Parametros!$D$23,Parametros!$C$24+(G59-Parametros!$E$24)*Parametros!$D$24))))))))) | H73: =IF(H59<=Parametros!$B$28,H59*Parametros!$D$28,IF(H59<=Parametros!$B$29,Parametros!$C$29+(H59-Parametros!$E$29)*Parametros!$D$29,IF(H59<=Parametros!$B$30,Parametros!$C$30+(H59-Parametros!$E$30)*Parametros!$D$30,IF(H59<=Parametros!$B$31,Parametros!$C$31+(H59-Parametros!$E$31)*Parametros!$D$31,IF(H59<=Parametros!$B$32,Parametros!$C$32+(H59-Parametros!$E$32)*Parametros!$D$32,IF(H59<=Parametros!$B$33,Parametros!$C$33+(H59-Parametros!$E$33)*Parametros!$D$33,IF(H59<=Parametros!$B$34,Parametros!$C$34+(H59-Parametros!$E$34)*Parametros!$D$34,IF(H59<=Parametros!$B$35,Parametros!$C$35+(H59-Parametros!$E$35)*Parametros!$D$35,IF(H59<=Parametros!$B$36,Parametros!$C$36+(H59-Parametros!$E$36)*Parametros!$D$36,Parametros!$C$37+(H59-Parametros!$E$37)*Parametros!$D$37))))))))) | I73: =IF(I59<=Parametros!$B$28,I59*Parametros!$D$28,IF(I59<=Parametros!$B$29,Parametros!$C$29+(I59-Parametros!$E$29)*Parametros!$D$29,IF(I59<=Parametros!$B$30,Parametros!$C$30+(I59-Parametros!$E$30)*Parametros!$D$30,IF(I59<=Parametros!$B$31,Parametros!$C$31+(I59-Parametros!$E$31)*Parametros!$D$31,IF(I59<=Parametros!$B$32,Parametros!$C$32+(I59-Parametros!$E$32)*Parametros!$D$32,IF(I59<=Parametros!$B$33,Parametros!$C$33+(I59-Parametros!$E$33)*Parametros!$D$33,IF(I59<=Parametros!$B$34,Parametros!$C$34+(I59-Parametros!$E$34)*Parametros!$D$34,IF(I59<=Parametros!$B$35,Parametros!$C$35+(I59-Parametros!$E$35)*Parametros!$D$35,IF(I59<=Parametros!$B$36,Parametros!$C$36+(I59-Parametros!$E$36)*Parametros!$D$36,Parametros!$C$37+(I59-Parametros!$E$37)*Parametros!$D$37))))))))) | J73: =IF(J59<=Parametros!$B$28,J59*Parametros!$D$28,IF(J59<=Parametros!$B$29,Parametros!$C$29+(J59-Parametros!$E$29)*Parametros!$D$29,IF(J59<=Parametros!$B$30,Parametros!$C$30+(J59-Parametros!$E$30)*Parametros!$D$30,IF(J59<=Parametros!$B$31,Parametros!$C$31+(J59-Parametros!$E$31)*Parametros!$D$31,IF(J59<=Parametros!$B$32,Parametros!$C$32+(J59-Parametros!$E$32)*Parametros!$D$32,IF(J59<=Parametros!$B$33,Parametros!$C$33+(J59-Parametros!$E$33)*Parametros!$D$33,IF(J59<=Parametros!$B$34,Parametros!$C$34+(J59-Parametros!$E$34)*Parametros!$D$34,IF(J59<=Parametros!$B$35,Parametros!$C$35+(J59-Parametros!$E$35)*Parametros!$D$35,IF(J59<=Parametros!$B$36,Parametros!$C$36+(J59-Parametros!$E$36)*Parametros!$D$36,Parametros!$C$37+(J59-Parametros!$E$37)*Parametros!$D$37))))))))) | K73: =IF(K59<=Parametros!$B$28,K59*Parametros!$D$28,IF(K59<=Parametros!$B$29,Parametros!$C$29+(K59-Parametros!$E$29)*Parametros!$D$29,IF(K59<=Parametros!$B$30,Parametros!$C$30+(K59-Parametros!$E$30)*Parametros!$D$30,IF(K59<=Parametros!$B$31,Parametros!$C$31+(K59-Parametros!$E$31)*Parametros!$D$31,IF(K59<=Parametros!$B$32,Parametros!$C$32+(K59-Parametros!$E$32)*Parametros!$D$32,IF(K59<=Parametros!$B$33,Parametros!$C$33+(K59-Parametros!$E$33)*Parametros!$D$33,IF(K59<=Parametros!$B$34,Parametros!$C$34+(K59-Parametros!$E$34)*Parametros!$D$34,IF(K59<=Parametros!$B$35,Parametros!$C$35+(K59-Parametros!$E$35)*Parametros!$D$35,IF(K59<=Parametros!$B$36,Parametros!$C$36+(K59-Parametros!$E$36)*Parametros!$D$36,Parametros!$C$37+(K59-Parametros!$E$37)*Parametros!$D$37))))))))) | L73: =IF(L59<=Parametros!$B$28,L59*Parametros!$D$28,IF(L59<=Parametros!$B$29,Parametros!$C$29+(L59-Parametros!$E$29)*Parametros!$D$29,IF(L59<=Parametros!$B$30,Parametros!$C$30+(L59-Parametros!$E$30)*Parametros!$D$30,IF(L59<=Parametros!$B$31,Parametros!$C$31+(L59-Parametros!$E$31)*Parametros!$D$31,IF(L59<=Parametros!$B$32,Parametros!$C$32+(L59-Parametros!$E$32)*Parametros!$D$32,IF(L59<=Parametros!$B$33,Parametros!$C$33+(L59-Parametros!$E$33)*Parametros!$D$33,IF(L59<=Parametros!$B$34,Parametros!$C$34+(L59-Parametros!$E$34)*Parametros!$D$34,IF(L59<=Parametros!$B$35,Parametros!$C$35+(L59-Parametros!$E$35)*Parametros!$D$35,IF(L59<=Parametros!$B$36,Parametros!$C$36+(L59-Parametros!$E$36)*Parametros!$D$36,Parametros!$C$37+(L59-Parametros!$E$37)*Parametros!$D$37))))))))) | M73: =IF(M59<=Parametros!$B$28,M59*Parametros!$D$28,IF(M59<=Parametros!$B$29,Parametros!$C$29+(M59-Parametros!$E$29)*Parametros!$D$29,IF(M59<=Parametros!$B$30,Parametros!$C$30+(M59-Parametros!$E$30)*Parametros!$D$30,IF(M59<=Parametros!$B$31,Parametros!$C$31+(M59-Parametros!$E$31)*Parametros!$D$31,IF(M59<=Parametros!$B$32,Parametros!$C$32+(M59-Parametros!$E$32)*Parametros!$D$32,IF(M59<=Parametros!$B$33,Parametros!$C$33+(M59-Parametros!$E$33)*Parametros!$D$33,IF(M59<=Parametros!$B$34,Parametros!$C$34+(M59-Parametros!$E$34)*Parametros!$D$34,IF(M59<=Parametros!$B$35,Parametros!$C$35+(M59-Parametros!$E$35)*Parametros!$D$35,IF(M59<=Parametros!$B$36,Parametros!$C$36+(M59-Parametros!$E$36)*Parametros!$D$36,Parametros!$C$37+(M59-Parametros!$E$37)*Parametros!$D$37)))))))))
A74: Impuesto Retenido Meses Anteriores | B74: 0 | C74: =B64+B67 | D74: =C64+C67 | E74: =D64+D67 | F74: =E64+E67 | G74: =F64+F67 | H74: =G64+G67 | I74: =H64+H67 | J74: =I64+I67 | ... M74: =L64+L67
A75: Pagos a Cuenta (Apartado G) | B75: 0 | C75: 0 | D75: 0 | E75: 0 | F75: 0 | G75: 0 | H75: 0 | I75: 0 | J75: 0 | K75: 0 | L75: 0 | M75: 0
A76: Retenciones Reintegradas (Apartado H) | B76: 0 | C76: 0 | D76: 0 | E76: 0 | F76: 0 | G76: 0 | H76: 0 | I76: 0 | J76: 0 | K76: 0 | L76: 0 | M76: 0
A77: Retención del Mes (antes de tope) | B77: =MAX(B63-B65-B64+B66,0) | C77: =MAX(C63-C65-C64+C66,0) | D77: =MAX(D63-D65-D64+D66,0) | E77: =MAX(E63-E65-E64+E66,0) | F77: =MAX(F63-F65-F64+F66,0) | G77: =MAX(G63-G65-G64+G66,0) | H77: =MAX(H63-H65-H64+H66,0) | I77: =MAX(I63-I65-I64+I66,0) | ... M77: =MAX(M63-M65-M64+M66,0)
A78: Tope 35% (Ganancia Bruta × 0.35) | B78: =B30*0.35 | C78: =C30*0.35 | D78: =D30*0.35 | E78: =E30*0.35 | F78: =F30*0.35 | G78: =G30*0.35 | H78: =H30*0.35 | I78: =I30*0.35 | ... M78: =M30*0.35
A79: Retención Efectiva | B79: =MIN(B65,B66) | C79: =MIN(C65,C66) | D79: =MIN(D65,D66) | E79: =MIN(E65,E66) | F79: =MIN(F65,F66) | G79: =MIN(G65,G66) | H79: =MIN(H65,H66) | I79: =MIN(I65,I66) | ... M79: =MIN(M65,M66)
A80: Diferencia no retenida (posterga) | B80: =B65-B67 | C80: =C65-C67 | D80: =D65-D67 | E80: =E65-E67 | F80: =F65-F67 | G80: =G65-G67 | H80: =H65-H67 | I80: =I65-I67 | ... M80: =M65-M67
A81: 9. SUELDO NETO
A82: Sueldo Neto | B82: =B13+B18-B25-B67 | C82: =C13+C18-C25-C67 | D82: =D13+D18-D25-D67 | E82: =E13+E18-E25-E67 | F82: =F13+F18-F25-F67 | G82: =G13+G18-G25-G67 | H82: =H13+H18-H25-H67 | I82: =I13+I18-I25-I67 | ... M82: =M13+M18-M25-M67

Sheet Instrucciones
A1: 📊 CALCULADORA DE RETENCIONES DE GANANCIAS 2025 - GUÍA DE USO COMPLETA
A3: 🎯 INTRODUCCIÓN
A4: Esta calculadora implementa el 100% del esquema de retenciones del Impuesto a las Ganancias 2025 según normativa ARCA (ex-AFIP), incluyendo:
A5: • Escalas progresivas actualizadas (Art. 94) para Enero-Junio 2025 y Julio-Diciembre 2025
A6: • Cálculo de SAC Proporcional mensual y Ajuste SAC Semestral (junio/diciembre)
A7: • Deducciones generales: Jubilación 11%, Obra Social 3%, INSSJP 3%, Aportes Sindicales
A8: • Deducciones especiales: Alquiler 40% + 10% (Ley 27.737), Medicina Prepaga 5%, Educación, Seguro de Vida, Donaciones, etc.
A9: • Deducciones personales: Ganancia No Imponible, Cónyuge, Hijos, Deducción Especial + Incremento 22% (Ley 27.743)
A10: • Pluriempleo (múltiples empleadores simultáneos)
A11: • Pagos a Cuenta (Apartado G)
A12: • Retenciones Reintegradas (Apartado H)
A13: • Tope de retención del 35% sobre sueldo neto
... A248: ════════════════════════════════════════════════════════════════════════════════

Sheet Resumen cálculo
B5: DETERMINACIÓN DEL IMPORTE A RETENER
B7: 1. Ganancia bruta del mes que se liquida (Apartado A) $ ........
B9: 2. Retribuciones no habituales de dicho mes (Apartado B) $ ........
B11: 3. Ganancia Sueldo Anual Complementario (Apartado C) $ ........
B13: 4. Deducciones a computar (Apartado D) $ (........)
B15: 5. Deducción Sueldo Anual Complementario (Apartado C) $ (........)
B17: 6. Ganancia neta del mes que se liquida $ =====
B19: 7. Ganancia neta de meses anteriores (dentro del mismo período fiscal) $ ........
B21: 8. Ganancia neta acumulada al mes que se liquida $ =====
B23: 9. Deducciones personales acumuladas al mes que se liquida (Apartado E):
B25: Ganancias no imponibles $ (........)
B27: Cargas de familia $ (........)
... B43: 15. Importe a retener/reintegrar en dicho mes $ =====
